pyramid_google_login/__init__.py
pyramid_google_login/events.py
pyramid_google_login/exceptions.py
pyramid_google_login/utility.py
pyramid_google_login/views.py
pyramid_google_login/static/login.css
pyramid_google_login/static/pure-min.css
pyramid_google_login/templates/signin.mako
pyramid_google_login/tests/__init__.py
pyramid_google_login/tests/functional/__init__.py
pyramid_google_login/tests/functional/test_flow.py
pyramid_google_login/tests/functional/test_utility.py
pyramid_google_login/tests/unittests/__init__.py
pyramid_google_login/tests/unittests/test_init.py
pyramid_google_login/tests/unittests/test_views.py
pyramid_google_login-1.2.0.dist-info/METADATA
pyramid_google_login-1.2.0.dist-info/RECORD
pyramid_google_login-1.2.0.dist-info/WHEEL
pyramid_google_login-1.2.0.dist-info/top_level.txt
