Metadata-Version: 2.1
Name: pyramid-google-login
Version: 1.2.0
Summary: Google Login for Pyramid
Home-page: https://github.com/ludia/pyramid_google_login
Author: Pior Bastida
Author-email: pior@pbastida.net
License: BSD-derived (http://www.repoze.org/LICENSE.txt)
Keywords: google,login,wsgi,pyramid,auth,authentication
Platform: UNKNOWN
Classifier: Development Status :: 5 - Production/Stable
Classifier: Intended Audience :: Developers
Classifier: Programming Language :: Python
Classifier: Programming Language :: Python :: 2
Classifier: Programming Language :: Python :: 2.7
Classifier: Programming Language :: Python :: 3
Classifier: Programming Language :: Python :: 3.5
Classifier: Programming Language :: Python :: 3.6
Classifier: Framework :: Pyramid
Classifier: Topic :: Internet :: WWW/HTTP :: WSGI
Requires-Dist: pyramid-mako
Requires-Dist: requests
Requires-Dist: six
